yiffscraper/__init__.py
yiffscraper/__main__.py
yiffscraper/downloader.py
yiffscraper/yiffscraper.py
yiffscraper-1.0.1.dist-info/LICENSE
yiffscraper-1.0.1.dist-info/METADATA
yiffscraper-1.0.1.dist-info/WHEEL
yiffscraper-1.0.1.dist-info/entry_points.txt
yiffscraper-1.0.1.dist-info/top_level.txt
yiffscraper-1.0.1.dist-info/RECORD
