Metadata-Version: 2.1
Name: yiffscraper
Version: 1.0.1
Summary: Scrapes off all content from a yiff.party page
Home-page: https://github.com/yiffscraper/yiffscraper
Author: Natalie Fearnley
Author-email: nfearnley@gmail.com
License: UNKNOWN
Platform: UNKNOWN
Classifier: Programming Language :: Python :: 3.6
Classifier: Operating System :: OS Independent
Classifier: License :: OSI Approved :: MIT License
Requires-Python: >=3.6
Requires-Dist: beautifulsoup4 (==4.8.1)
Requires-Dist: requests (==2.22.0)
Requires-Dist: tqdm (==4.40.0)
Requires-Dist: aiohttp (==3.6.2)
Requires-Dist: python-dateutil (==2.8.1)
